{
  "date": "2026-02-20",
  "games": [
    {
      "away_team": "Milwaukee",
      "edge_home_points": 3.5943312644958496,
      "game_id": "2026_02_20_milwaukee_detroit_mercy",
      "home_team": "Detroit Mercy",
      "market_spread_home": -1.5,
      "model_mu_home": -5.0943313,
      "neutral_site": 0,
      "pick_cover_prob": 0.6540360541982335,
      "pick_ev_per_1": 0.2486142852875367,
      "pick_fair_odds": -189.04746061978057,
      "pick_prob_edge": 0.13022653038870968,
      "pick_side": "HOME",
      "pick_spread_odds": -110.0,
      "pred_home_win_prob": 0.7128059021759632,
      "pred_sigma": 9.071094
    },
    {
      "away_team": "Green Bay",
      "edge_home_points": -2.994239568710327,
      "game_id": "2026_02_20_green_bay_oakland",
      "home_team": "Oakland",
      "market_spread_home": -6.5,
      "model_mu_home": -3.5057604,
      "neutral_site": 0,
      "pick_cover_prob": 0.6476546079699689,
      "pick_ev_per_1": 0.21083252794385487,
      "pick_fair_odds": -183.81242457536325,
      "pick_prob_edge": 0.11277088703973637,
      "pick_side": "AWAY",
      "pick_spread_odds": -115.0,
      "pred_home_win_prob": 0.6713853841108177,
      "pred_sigma": 7.90045
    },
    {
      "away_team": "Marist",
      "edge_home_points": -2.780930519104004,
      "game_id": "2026_02_20_marist_manhattan",
      "home_team": "Manhattan",
      "market_spread_home": 4.5,
      "model_mu_home": 7.2809305,
      "neutral_site": 0,
      "pick_cover_prob": 0.6097449951910081,
      "pick_ev_per_1": 0.13995803448753685,
      "pick_fair_odds": -156.24270994024647,
      "pick_prob_edge": 0.0748612742607756,
      "pick_side": "AWAY",
      "pick_spread_odds": -115.0,
      "pred_home_win_prob": 0.2328286954204274,
      "pred_sigma": 9.979853
    },
    {
      "away_team": "Indiana",
      "edge_home_points": -2.052898406982422,
      "game_id": "2026_02_20_indiana_purdue",
      "home_team": "Purdue",
      "market_spread_home": -11.5,
      "model_mu_home": -9.447102,
      "neutral_site": 0,
      "pick_cover_prob": 0.5828736402833431,
      "pick_ev_per_1": 0.13799139293414597,
      "pick_fair_odds": -139.73550860685813,
      "pick_prob_edge": 0.07067851833212357,
      "pick_side": "AWAY",
      "pick_spread_odds": -105.0,
      "pred_home_win_prob": 0.8322102541390198,
      "pred_sigma": 9.810723
    },
    {
      "away_team": "Princeton",
      "edge_home_points": -1.6891799867153168,
      "game_id": "2026_02_20_princeton_brown",
      "home_team": "Brown",
      "market_spread_home": -1.5,
      "model_mu_home": 0.18917999,
      "neutral_site": 0,
      "pick_cover_prob": 0.5751391416706335,
      "pick_ev_per_1": 0.12289070516647493,
      "pick_fair_odds": -135.37117632633652,
      "pick_prob_edge": 0.06294401971941399,
      "pick_side": "AWAY",
      "pick_spread_odds": -105.0,
      "pred_home_win_prob": 0.4915350337195119,
      "pred_sigma": 8.915125
    },
    {
      "away_team": "Niagara",
      "edge_home_points": -1.447866439819336,
      "game_id": "2026_02_20_niagara_mount_st_mary_s",
      "home_team": "Mount St. Mary's",
      "market_spread_home": -6.5,
      "model_mu_home": -5.0521336,
      "neutral_site": 0,
      "pick_cover_prob": 0.5638609974712667,
      "pick_ev_per_1": 0.07646190426332733,
      "pick_fair_odds": -129.28469919039605,
      "pick_prob_edge": 0.04005147366174289,
      "pick_side": "AWAY",
      "pick_spread_odds": -110.0,
      "pred_home_win_prob": 0.7125909449510341,
      "pred_sigma": 9.00607
    },
    {
      "away_team": "Bowling Green",
      "edge_home_points": 1.5311918258666992,
      "game_id": "2026_02_20_bowling_green_miami_oh",
      "home_team": "Miami OH",
      "market_spread_home": -7.5,
      "model_mu_home": -9.031192,
      "neutral_site": 0,
      "pick_cover_prob": 0.5686690793649929,
      "pick_ev_per_1": 0.06316393098672585,
      "pick_fair_odds": -131.8405549335058,
      "pick_prob_edge": 0.03378535843476038,
      "pick_side": "HOME",
      "pick_spread_odds": -115.0,
      "pred_home_win_prob": 0.8462071332968257,
      "pred_sigma": 8.851498
    },
    {
      "away_team": "VCU",
      "edge_home_points": -1.0870165824890137,
      "game_id": "2026_02_20_vcu_saint_louis",
      "home_team": "Saint Louis",
      "market_spread_home": -7.5,
      "model_mu_home": -6.4129834,
      "neutral_site": 0,
      "pick_cover_prob": 0.5451896149069448,
      "pick_ev_per_1": 0.040816537549621945,
      "pick_fair_odds": -119.87184830781688,
      "pick_prob_edge": 0.021380091097421006,
      "pick_side": "AWAY",
      "pick_spread_odds": -110.0,
      "pred_home_win_prob": 0.748477513467805,
      "pred_sigma": 9.575813
    },
    {
      "away_team": "Sacred Heart",
      "edge_home_points": -0.4221482276916504,
      "game_id": "2026_02_20_sacred_heart_fairfield",
      "home_team": "Fairfield",
      "market_spread_home": -4.5,
      "model_mu_home": -4.077852,
      "neutral_site": 0,
      "pick_cover_prob": 0.5167798423248269,
      "pick_ev_per_1": 0.033559684649653754,
      "pick_fair_odds": -106.94500925025834,
      "pick_prob_edge": 0.016779842324826877,
      "pick_side": "AWAY",
      "pick_spread_odds": 100.0,
      "pred_home_win_prob": 0.6577820640896699,
      "pred_sigma": 10.033652
    },
    {
      "away_team": "Saint Peter's",
      "edge_home_points": -1.1402230560779572,
      "game_id": "2026_02_20_saint_peter_s_iona",
      "home_team": "Iona",
      "market_spread_home": -1.5,
      "model_mu_home": -0.35977694,
      "neutral_site": 0,
      "pick_cover_prob": 0.5506734147414915,
      "pick_ev_per_1": 0.02951986234278836,
      "pick_fair_odds": -122.55527111191864,
      "pick_prob_edge": 0.015789693811258942,
      "pick_side": "AWAY",
      "pick_spread_odds": -115.0,
      "pred_home_win_prob": 0.5160280122074659,
      "pred_sigma": 8.952552
    },
    {
      "away_team": "Canisius",
      "edge_home_points": 0.510360062122345,
      "game_id": "2026_02_20_canisius_rider",
      "home_team": "Rider",
      "market_spread_home": 1.5,
      "model_mu_home": 0.98963994,
      "neutral_site": 0,
      "pick_cover_prob": 0.5211606901528634,
      "pick_ev_per_1": -0.0050568642536245045,
      "pick_fair_odds": -108.83832622664946,
      "pick_prob_edge": -0.0026488336566604653,
      "pick_side": "HOME",
      "pick_spread_odds": -110.0,
      "pred_home_win_prob": 0.459020349268163,
      "pred_sigma": 9.617299
    },
    {
      "away_team": "Akron",
      "edge_home_points": -0.08785343170166016,
      "game_id": "2026_02_20_akron_ball_st",
      "home_team": "Ball St.",
      "market_spread_home": 14.5,
      "model_mu_home": 14.587853,
      "neutral_site": 0,
      "pick_cover_prob": 0.5028716722152635,
      "pick_ev_per_1": -0.03997226213449695,
      "pick_fair_odds": -101.15530419602521,
      "pick_prob_edge": -0.020937851594260315,
      "pick_side": "AWAY",
      "pick_spread_odds": -110.0,
      "pred_home_win_prob": 0.1159933624899222,
      "pred_sigma": 12.204786
    },
    {
      "away_team": "Siena",
      "edge_home_points": 0.20931673049926758,
      "game_id": "2026_02_20_siena_merrimack",
      "home_team": "Merrimack",
      "market_spread_home": -3.5,
      "model_mu_home": -3.7093167,
      "neutral_site": 0,
      "pick_cover_prob": 0.5121225304882576,
      "pick_ev_per_1": -0.04255352995673578,
      "pick_fair_odds": -104.96949797677257,
      "pick_prob_edge": -0.022761190441974888,
      "pick_side": "HOME",
      "pick_spread_odds": -115.0,
      "pred_home_win_prob": 0.7049072998275192,
      "pred_sigma": 6.8873773
    }
  ],
  "generated_at": "2026-02-20T15:32:53.920525Z"
}
