{
  "date": "2025-12-10",
  "games": [
    {
      "away_team": "Tennessee Martin",
      "edge_home_points": null,
      "game_id": "2025_12_10_tennessee_martin_southern_illinois",
      "home_team": "Southern Illinois",
      "market_spread_home": null,
      "model_mu_home": -9.528768,
      "neutral_site": 0,
      "pick_cover_prob": null,
      "pick_ev_per_1": null,
      "pick_fair_odds": null,
      "pick_prob_edge": null,
      "pick_side": "AWAY",
      "pick_spread_odds": null,
      "pred_home_win_prob": 0.8205296609795989,
      "pred_sigma": 10.386874
    },
    {
      "away_team": "Liberty",
      "edge_home_points": null,
      "game_id": "2025_12_10_liberty_n_c_state",
      "home_team": "N.C. State",
      "market_spread_home": null,
      "model_mu_home": -9.8392105,
      "neutral_site": 0,
      "pick_cover_prob": null,
      "pick_ev_per_1": null,
      "pick_fair_odds": null,
      "pick_prob_edge": null,
      "pick_side": "AWAY",
      "pick_spread_odds": null,
      "pred_home_win_prob": 0.8369557837917937,
      "pred_sigma": 10.019326
    },
    {
      "away_team": "Boston College",
      "edge_home_points": null,
      "game_id": "2025_12_10_boston_college_massachusetts",
      "home_team": "Massachusetts",
      "market_spread_home": null,
      "model_mu_home": 2.833873,
      "neutral_site": 1,
      "pick_cover_prob": null,
      "pick_ev_per_1": null,
      "pick_fair_odds": null,
      "pick_prob_edge": null,
      "pick_side": "AWAY",
      "pick_spread_odds": null,
      "pred_home_win_prob": 0.38271813148458106,
      "pred_sigma": 9.498494
    },
    {
      "away_team": "Miami OH",
      "edge_home_points": null,
      "game_id": "2025_12_10_miami_oh_unc_asheville",
      "home_team": "UNC Asheville",
      "market_spread_home": null,
      "model_mu_home": 4.038388,
      "neutral_site": 0,
      "pick_cover_prob": null,
      "pick_ev_per_1": null,
      "pick_fair_odds": null,
      "pick_prob_edge": null,
      "pick_side": "AWAY",
      "pick_spread_odds": null,
      "pred_home_win_prob": 0.3331956279510857,
      "pred_sigma": 9.367504
    },
    {
      "away_team": "Wisconsin",
      "edge_home_points": null,
      "game_id": "2025_12_10_wisconsin_nebraska",
      "home_team": "Nebraska",
      "market_spread_home": null,
      "model_mu_home": -2.5425043,
      "neutral_site": 0,
      "pick_cover_prob": null,
      "pick_ev_per_1": null,
      "pick_fair_odds": null,
      "pick_prob_edge": null,
      "pick_side": "AWAY",
      "pick_spread_odds": null,
      "pred_home_win_prob": 0.5975226726908495,
      "pred_sigma": 10.296041
    },
    {
      "away_team": "Bryant",
      "edge_home_points": null,
      "game_id": "2025_12_10_bryant_iona",
      "home_team": "Iona",
      "market_spread_home": null,
      "model_mu_home": -11.886485,
      "neutral_site": 0,
      "pick_cover_prob": null,
      "pick_ev_per_1": null,
      "pick_fair_odds": null,
      "pick_prob_edge": null,
      "pick_side": "AWAY",
      "pick_spread_odds": null,
      "pred_home_win_prob": 0.8860176440690115,
      "pred_sigma": 9.859244
    },
    {
      "away_team": "Jackson St.",
      "edge_home_points": null,
      "game_id": "2025_12_10_jackson_st_houston",
      "home_team": "Houston",
      "market_spread_home": null,
      "model_mu_home": -27.589981,
      "neutral_site": 0,
      "pick_cover_prob": null,
      "pick_ev_per_1": null,
      "pick_fair_odds": null,
      "pick_prob_edge": null,
      "pick_side": "AWAY",
      "pick_spread_odds": null,
      "pred_home_win_prob": 0.9833365843652377,
      "pred_sigma": 12.964463
    },
    {
      "away_team": "Lamar",
      "edge_home_points": null,
      "game_id": "2025_12_10_lamar_san_diego_st",
      "home_team": "San Diego St.",
      "market_spread_home": null,
      "model_mu_home": -14.898845,
      "neutral_site": 0,
      "pick_cover_prob": null,
      "pick_ev_per_1": null,
      "pick_fair_odds": null,
      "pick_prob_edge": null,
      "pick_side": "AWAY",
      "pick_spread_odds": null,
      "pred_home_win_prob": 0.9119391244224606,
      "pred_sigma": 11.013395
    },
    {
      "away_team": "Minnesota",
      "edge_home_points": null,
      "game_id": "2025_12_10_minnesota_purdue",
      "home_team": "Purdue",
      "market_spread_home": null,
      "model_mu_home": -13.748672,
      "neutral_site": 0,
      "pick_cover_prob": null,
      "pick_ev_per_1": null,
      "pick_fair_odds": null,
      "pick_prob_edge": null,
      "pick_side": "AWAY",
      "pick_spread_odds": null,
      "pred_home_win_prob": 0.9173962955124558,
      "pred_sigma": 9.907032
    },
    {
      "away_team": "Maine",
      "edge_home_points": null,
      "game_id": "2025_12_10_maine_boston_university",
      "home_team": "Boston University",
      "market_spread_home": null,
      "model_mu_home": -8.778097,
      "neutral_site": 0,
      "pick_cover_prob": null,
      "pick_ev_per_1": null,
      "pick_fair_odds": null,
      "pick_prob_edge": null,
      "pick_side": "AWAY",
      "pick_spread_odds": null,
      "pred_home_win_prob": 0.8187356528732677,
      "pred_sigma": 9.640357
    },
    {
      "away_team": "Albany",
      "edge_home_points": null,
      "game_id": "2025_12_10_albany_yale",
      "home_team": "Yale",
      "market_spread_home": null,
      "model_mu_home": -17.71009,
      "neutral_site": 1,
      "pick_cover_prob": null,
      "pick_ev_per_1": null,
      "pick_fair_odds": null,
      "pick_prob_edge": null,
      "pick_side": "AWAY",
      "pick_spread_odds": null,
      "pred_home_win_prob": 0.9330650622430001,
      "pred_sigma": 11.814489
    },
    {
      "away_team": "Eastern Kentucky",
      "edge_home_points": null,
      "game_id": "2025_12_10_eastern_kentucky_eastern_illinois",
      "home_team": "Eastern Illinois",
      "market_spread_home": null,
      "model_mu_home": 3.3305907,
      "neutral_site": 0,
      "pick_cover_prob": null,
      "pick_ev_per_1": null,
      "pick_fair_odds": null,
      "pick_prob_edge": null,
      "pick_side": "AWAY",
      "pick_spread_odds": null,
      "pred_home_win_prob": 0.3521215713487999,
      "pred_sigma": 8.7739725
    },
    {
      "away_team": "Weber St.",
      "edge_home_points": null,
      "game_id": "2025_12_10_weber_st_umkc",
      "home_team": "UMKC",
      "market_spread_home": null,
      "model_mu_home": 6.0897636,
      "neutral_site": 0,
      "pick_cover_prob": null,
      "pick_ev_per_1": null,
      "pick_fair_odds": null,
      "pick_prob_edge": null,
      "pick_side": "AWAY",
      "pick_spread_odds": null,
      "pred_home_win_prob": 0.2592475012202001,
      "pred_sigma": 9.43174
    },
    {
      "away_team": "Charleston",
      "edge_home_points": null,
      "game_id": "2025_12_10_charleston_south_florida",
      "home_team": "South Florida",
      "market_spread_home": null,
      "model_mu_home": -16.4764,
      "neutral_site": 0,
      "pick_cover_prob": null,
      "pick_ev_per_1": null,
      "pick_fair_odds": null,
      "pick_prob_edge": null,
      "pick_side": "AWAY",
      "pick_spread_odds": null,
      "pred_home_win_prob": 0.9158305602449662,
      "pred_sigma": 11.96056
    },
    {
      "away_team": "Idaho St.",
      "edge_home_points": null,
      "game_id": "2025_12_10_idaho_st_utah_valley",
      "home_team": "Utah Valley",
      "market_spread_home": null,
      "model_mu_home": -11.377435,
      "neutral_site": 0,
      "pick_cover_prob": null,
      "pick_ev_per_1": null,
      "pick_fair_odds": null,
      "pick_prob_edge": null,
      "pick_side": "AWAY",
      "pick_spread_odds": null,
      "pred_home_win_prob": 0.8927827044194202,
      "pred_sigma": 9.164535
    },
    {
      "away_team": "Duquesne",
      "edge_home_points": null,
      "game_id": "2025_12_10_duquesne_boise_st",
      "home_team": "Boise St.",
      "market_spread_home": null,
      "model_mu_home": -12.135755,
      "neutral_site": 0,
      "pick_cover_prob": null,
      "pick_ev_per_1": null,
      "pick_fair_odds": null,
      "pick_prob_edge": null,
      "pick_side": "AWAY",
      "pick_spread_odds": null,
      "pred_home_win_prob": 0.9082431409192961,
      "pred_sigma": 9.124533
    },
    {
      "away_team": "Fresno St.",
      "edge_home_points": null,
      "game_id": "2025_12_10_fresno_st_cal_st_northridge",
      "home_team": "Cal St. Northridge",
      "market_spread_home": null,
      "model_mu_home": 0.3911148,
      "neutral_site": 0,
      "pick_cover_prob": null,
      "pick_ev_per_1": null,
      "pick_fair_odds": null,
      "pick_prob_edge": null,
      "pick_side": "AWAY",
      "pick_spread_odds": null,
      "pred_home_win_prob": 0.4832328221063137,
      "pred_sigma": 9.303073
    },
    {
      "away_team": "Norfolk St.",
      "edge_home_points": null,
      "game_id": "2025_12_10_norfolk_st_baylor",
      "home_team": "Baylor",
      "market_spread_home": null,
      "model_mu_home": -22.084024,
      "neutral_site": 0,
      "pick_cover_prob": null,
      "pick_ev_per_1": null,
      "pick_fair_odds": null,
      "pick_prob_edge": null,
      "pick_side": "AWAY",
      "pick_spread_odds": null,
      "pred_home_win_prob": 0.9577317610580932,
      "pred_sigma": 12.802704
    },
    {
      "away_team": "Colgate",
      "edge_home_points": null,
      "game_id": "2025_12_10_colgate_st_bonaventure",
      "home_team": "St. Bonaventure",
      "market_spread_home": null,
      "model_mu_home": -7.8821607,
      "neutral_site": 0,
      "pick_cover_prob": null,
      "pick_ev_per_1": null,
      "pick_fair_odds": null,
      "pick_prob_edge": null,
      "pick_side": "AWAY",
      "pick_spread_odds": null,
      "pred_home_win_prob": 0.8166649174162713,
      "pred_sigma": 8.731488
    },
    {
      "away_team": "Eastern Michigan",
      "edge_home_points": null,
      "game_id": "2025_12_10_eastern_michigan_purdue_fort_wayne",
      "home_team": "Purdue Fort Wayne",
      "market_spread_home": null,
      "model_mu_home": -0.2635613,
      "neutral_site": 0,
      "pick_cover_prob": null,
      "pick_ev_per_1": null,
      "pick_fair_odds": null,
      "pick_prob_edge": null,
      "pick_side": "AWAY",
      "pick_spread_odds": null,
      "pred_home_win_prob": 0.5097376852537387,
      "pred_sigma": 10.796745
    },
    {
      "away_team": "Delaware",
      "edge_home_points": null,
      "game_id": "2025_12_10_delaware_george_washington",
      "home_team": "George Washington",
      "market_spread_home": null,
      "model_mu_home": -20.636919,
      "neutral_site": 0,
      "pick_cover_prob": null,
      "pick_ev_per_1": null,
      "pick_fair_odds": null,
      "pick_prob_edge": null,
      "pick_side": "AWAY",
      "pick_spread_odds": null,
      "pred_home_win_prob": 0.9531679131366104,
      "pred_sigma": 12.310421
    },
    {
      "away_team": "Fairleigh Dickinson",
      "edge_home_points": null,
      "game_id": "2025_12_10_fairleigh_dickinson_fordham",
      "home_team": "Fordham",
      "market_spread_home": null,
      "model_mu_home": -14.709096,
      "neutral_site": 0,
      "pick_cover_prob": null,
      "pick_ev_per_1": null,
      "pick_fair_odds": null,
      "pick_prob_edge": null,
      "pick_side": "AWAY",
      "pick_spread_odds": null,
      "pred_home_win_prob": 0.9124963319738015,
      "pred_sigma": 10.845107
    },
    {
      "away_team": "Idaho",
      "edge_home_points": null,
      "game_id": "2025_12_10_idaho_notre_dame",
      "home_team": "Notre Dame",
      "market_spread_home": null,
      "model_mu_home": -10.930059,
      "neutral_site": 0,
      "pick_cover_prob": null,
      "pick_ev_per_1": null,
      "pick_fair_odds": null,
      "pick_prob_edge": null,
      "pick_side": "AWAY",
      "pick_spread_odds": null,
      "pred_home_win_prob": 0.8983400894108935,
      "pred_sigma": 8.591801
    },
    {
      "away_team": "Western Kentucky",
      "edge_home_points": null,
      "game_id": "2025_12_10_western_kentucky_marshall",
      "home_team": "Marshall",
      "market_spread_home": null,
      "model_mu_home": 2.2311485,
      "neutral_site": 0,
      "pick_cover_prob": null,
      "pick_ev_per_1": null,
      "pick_fair_odds": null,
      "pick_prob_edge": null,
      "pick_side": "AWAY",
      "pick_spread_odds": null,
      "pred_home_win_prob": 0.3963996823917323,
      "pred_sigma": 8.493878
    },
    {
      "away_team": "Arkansas Pine Bluff",
      "edge_home_points": null,
      "game_id": "2025_12_10_arkansas_pine_bluff_tulsa",
      "home_team": "Tulsa",
      "market_spread_home": null,
      "model_mu_home": -20.806362,
      "neutral_site": 0,
      "pick_cover_prob": null,
      "pick_ev_per_1": null,
      "pick_fair_odds": null,
      "pick_prob_edge": null,
      "pick_side": "AWAY",
      "pick_spread_odds": null,
      "pred_home_win_prob": 0.9619568698180088,
      "pred_sigma": 11.729425
    },
    {
      "away_team": "Merrimack",
      "edge_home_points": null,
      "game_id": "2025_12_10_merrimack_princeton",
      "home_team": "Princeton",
      "market_spread_home": null,
      "model_mu_home": -5.0140457,
      "neutral_site": 0,
      "pick_cover_prob": null,
      "pick_ev_per_1": null,
      "pick_fair_odds": null,
      "pick_prob_edge": null,
      "pick_side": "AWAY",
      "pick_spread_odds": null,
      "pred_home_win_prob": 0.682078818180242,
      "pred_sigma": 10.588882
    },
    {
      "away_team": "New Mexico",
      "edge_home_points": null,
      "game_id": "2025_12_10_new_mexico_vcu",
      "home_team": "VCU",
      "market_spread_home": null,
      "model_mu_home": -11.156894,
      "neutral_site": 0,
      "pick_cover_prob": null,
      "pick_ev_per_1": null,
      "pick_fair_odds": null,
      "pick_prob_edge": null,
      "pick_side": "AWAY",
      "pick_spread_odds": null,
      "pred_home_win_prob": 0.8769812722440053,
      "pred_sigma": 9.617781
    },
    {
      "away_team": "New Haven",
      "edge_home_points": null,
      "game_id": "2025_12_10_new_haven_njit",
      "home_team": "NJIT",
      "market_spread_home": null,
      "model_mu_home": 1.9615653,
      "neutral_site": 0,
      "pick_cover_prob": null,
      "pick_ev_per_1": null,
      "pick_fair_odds": null,
      "pick_prob_edge": null,
      "pick_side": "AWAY",
      "pick_spread_odds": null,
      "pred_home_win_prob": 0.4161064848326203,
      "pred_sigma": 9.258596
    },
    {
      "away_team": "Southern",
      "edge_home_points": null,
      "game_id": "2025_12_10_southern_texas_st",
      "home_team": "Texas St.",
      "market_spread_home": null,
      "model_mu_home": -1.6131113,
      "neutral_site": 0,
      "pick_cover_prob": null,
      "pick_ev_per_1": null,
      "pick_fair_odds": null,
      "pick_prob_edge": null,
      "pick_side": "AWAY",
      "pick_spread_odds": null,
      "pred_home_win_prob": 0.5852161041858999,
      "pred_sigma": 7.4939227
    }
  ],
  "generated_at": "2026-01-22T16:44:06.213623Z"
}
