{
  "date": "2025-11-30",
  "games": [
    {
      "away_team": "San Diego",
      "edge_home_points": null,
      "game_id": "2025_11_30_san_diego_long_beach_st",
      "home_team": "Long Beach St.",
      "market_spread_home": null,
      "model_mu_home": 4.158615,
      "neutral_site": 0,
      "pick_cover_prob": null,
      "pick_ev_per_1": null,
      "pick_fair_odds": null,
      "pick_prob_edge": null,
      "pick_side": "AWAY",
      "pick_spread_odds": null,
      "pred_home_win_prob": 0.3237339676689825,
      "pred_sigma": 9.094191
    },
    {
      "away_team": "Alabama A&M",
      "edge_home_points": null,
      "game_id": "2025_11_30_alabama_a_m_coastal_carolina",
      "home_team": "Coastal Carolina",
      "market_spread_home": null,
      "model_mu_home": -3.645593,
      "neutral_site": 0,
      "pick_cover_prob": null,
      "pick_ev_per_1": null,
      "pick_fair_odds": null,
      "pick_prob_edge": null,
      "pick_side": "AWAY",
      "pick_spread_odds": null,
      "pred_home_win_prob": 0.6566078231463773,
      "pred_sigma": 9.041139
    },
    {
      "away_team": "Presbyterian",
      "edge_home_points": null,
      "game_id": "2025_11_30_presbyterian_the_citadel",
      "home_team": "The Citadel",
      "market_spread_home": null,
      "model_mu_home": 6.7252703,
      "neutral_site": 1,
      "pick_cover_prob": null,
      "pick_ev_per_1": null,
      "pick_fair_odds": null,
      "pick_prob_edge": null,
      "pick_side": "AWAY",
      "pick_spread_odds": null,
      "pred_home_win_prob": 0.2642353819329047,
      "pred_sigma": 10.669238
    },
    {
      "away_team": "Monmouth",
      "edge_home_points": null,
      "game_id": "2025_11_30_monmouth_lafayette",
      "home_team": "Lafayette",
      "market_spread_home": null,
      "model_mu_home": 0.84138614,
      "neutral_site": 0,
      "pick_cover_prob": null,
      "pick_ev_per_1": null,
      "pick_fair_odds": null,
      "pick_prob_edge": null,
      "pick_side": "AWAY",
      "pick_spread_odds": null,
      "pred_home_win_prob": 0.465779487769106,
      "pred_sigma": 9.7968235
    },
    {
      "away_team": "Stetson",
      "edge_home_points": null,
      "game_id": "2025_11_30_stetson_robert_morris",
      "home_team": "Robert Morris",
      "market_spread_home": null,
      "model_mu_home": -13.780152,
      "neutral_site": 0,
      "pick_cover_prob": null,
      "pick_ev_per_1": null,
      "pick_fair_odds": null,
      "pick_prob_edge": null,
      "pick_side": "AWAY",
      "pick_spread_odds": null,
      "pred_home_win_prob": 0.9157818492336892,
      "pred_sigma": 10.005588
    },
    {
      "away_team": "Maine",
      "edge_home_points": null,
      "game_id": "2025_11_30_maine_siena",
      "home_team": "Siena",
      "market_spread_home": null,
      "model_mu_home": -12.3112335,
      "neutral_site": 1,
      "pick_cover_prob": null,
      "pick_ev_per_1": null,
      "pick_fair_odds": null,
      "pick_prob_edge": null,
      "pick_side": "AWAY",
      "pick_spread_odds": null,
      "pred_home_win_prob": 0.897335366576371,
      "pred_sigma": 9.72057
    },
    {
      "away_team": "Coppin St.",
      "edge_home_points": null,
      "game_id": "2025_11_30_coppin_st_loyola_md",
      "home_team": "Loyola MD",
      "market_spread_home": null,
      "model_mu_home": -9.157431,
      "neutral_site": 0,
      "pick_cover_prob": null,
      "pick_ev_per_1": null,
      "pick_fair_odds": null,
      "pick_prob_edge": null,
      "pick_side": "AWAY",
      "pick_spread_odds": null,
      "pred_home_win_prob": 0.8137060848160653,
      "pred_sigma": 10.270364
    },
    {
      "away_team": "Tennessee St.",
      "edge_home_points": null,
      "game_id": "2025_11_30_tennessee_st_chattanooga",
      "home_team": "Chattanooga",
      "market_spread_home": null,
      "model_mu_home": -5.419108,
      "neutral_site": 0,
      "pick_cover_prob": null,
      "pick_ev_per_1": null,
      "pick_fair_odds": null,
      "pick_prob_edge": null,
      "pick_side": "AWAY",
      "pick_spread_odds": null,
      "pred_home_win_prob": 0.6975284961339917,
      "pred_sigma": 10.475646
    },
    {
      "away_team": "Princeton",
      "edge_home_points": null,
      "game_id": "2025_11_30_princeton_saint_joseph_s",
      "home_team": "Saint Joseph's",
      "market_spread_home": null,
      "model_mu_home": -4.4523296,
      "neutral_site": 1,
      "pick_cover_prob": null,
      "pick_ev_per_1": null,
      "pick_fair_odds": null,
      "pick_prob_edge": null,
      "pick_side": "AWAY",
      "pick_spread_odds": null,
      "pred_home_win_prob": 0.6939890959315681,
      "pred_sigma": 8.778433
    },
    {
      "away_team": "Hofstra",
      "edge_home_points": null,
      "game_id": "2025_11_30_hofstra_penn",
      "home_team": "Penn",
      "market_spread_home": null,
      "model_mu_home": 0.7206257,
      "neutral_site": 0,
      "pick_cover_prob": null,
      "pick_ev_per_1": null,
      "pick_fair_odds": null,
      "pick_prob_edge": null,
      "pick_side": "AWAY",
      "pick_spread_odds": null,
      "pred_home_win_prob": 0.4715130625450207,
      "pred_sigma": 10.083342
    },
    {
      "away_team": "Appalachian St.",
      "edge_home_points": null,
      "game_id": "2025_11_30_appalachian_st_unc_asheville",
      "home_team": "UNC Asheville",
      "market_spread_home": null,
      "model_mu_home": -5.6942563,
      "neutral_site": 0,
      "pick_cover_prob": null,
      "pick_ev_per_1": null,
      "pick_fair_odds": null,
      "pick_prob_edge": null,
      "pick_side": "AWAY",
      "pick_spread_odds": null,
      "pred_home_win_prob": 0.7275333264379592,
      "pred_sigma": 9.406245
    },
    {
      "away_team": "Longwood",
      "edge_home_points": null,
      "game_id": "2025_11_30_longwood_american",
      "home_team": "American",
      "market_spread_home": null,
      "model_mu_home": -1.5631572,
      "neutral_site": 0,
      "pick_cover_prob": null,
      "pick_ev_per_1": null,
      "pick_fair_odds": null,
      "pick_prob_edge": null,
      "pick_side": "AWAY",
      "pick_spread_odds": null,
      "pred_home_win_prob": 0.5588962510162463,
      "pred_sigma": 10.549655
    },
    {
      "away_team": "Ball St.",
      "edge_home_points": null,
      "game_id": "2025_11_30_ball_st_le_moyne",
      "home_team": "Le Moyne",
      "market_spread_home": null,
      "model_mu_home": 1.4975677,
      "neutral_site": 1,
      "pick_cover_prob": null,
      "pick_ev_per_1": null,
      "pick_fair_odds": null,
      "pick_prob_edge": null,
      "pick_side": "AWAY",
      "pick_spread_odds": null,
      "pred_home_win_prob": 0.444096164902678,
      "pred_sigma": 10.6518755
    },
    {
      "away_team": "Mercyhurst",
      "edge_home_points": null,
      "game_id": "2025_11_30_mercyhurst_west_virginia",
      "home_team": "West Virginia",
      "market_spread_home": null,
      "model_mu_home": -21.215134,
      "neutral_site": 0,
      "pick_cover_prob": null,
      "pick_ev_per_1": null,
      "pick_fair_odds": null,
      "pick_prob_edge": null,
      "pick_side": "AWAY",
      "pick_spread_odds": null,
      "pred_home_win_prob": 0.9589904185971212,
      "pred_sigma": 12.198995
    },
    {
      "away_team": "Cal St. Bakersfield",
      "edge_home_points": null,
      "game_id": "2025_11_30_cal_st_bakersfield_fresno_st",
      "home_team": "Fresno St.",
      "market_spread_home": null,
      "model_mu_home": -7.746511,
      "neutral_site": 0,
      "pick_cover_prob": null,
      "pick_ev_per_1": null,
      "pick_fair_odds": null,
      "pick_prob_edge": null,
      "pick_side": "AWAY",
      "pick_spread_odds": null,
      "pred_home_win_prob": 0.7704635831750803,
      "pred_sigma": 10.462964
    },
    {
      "away_team": "La Salle",
      "edge_home_points": null,
      "game_id": "2025_11_30_la_salle_merrimack",
      "home_team": "Merrimack",
      "market_spread_home": null,
      "model_mu_home": 4.7811236,
      "neutral_site": 1,
      "pick_cover_prob": null,
      "pick_ev_per_1": null,
      "pick_fair_odds": null,
      "pick_prob_edge": null,
      "pick_side": "AWAY",
      "pick_spread_odds": null,
      "pred_home_win_prob": 0.3145171994072872,
      "pred_sigma": 9.897037
    },
    {
      "away_team": "Yale",
      "edge_home_points": null,
      "game_id": "2025_11_30_yale_vermont",
      "home_team": "Vermont",
      "market_spread_home": null,
      "model_mu_home": 8.059389,
      "neutral_site": 0,
      "pick_cover_prob": null,
      "pick_ev_per_1": null,
      "pick_fair_odds": null,
      "pick_prob_edge": null,
      "pick_side": "AWAY",
      "pick_spread_odds": null,
      "pred_home_win_prob": 0.2506398160532636,
      "pred_sigma": 11.984619
    },
    {
      "away_team": "Belmont",
      "edge_home_points": null,
      "game_id": "2025_11_30_belmont_charleston",
      "home_team": "Charleston",
      "market_spread_home": null,
      "model_mu_home": 3.5077085,
      "neutral_site": 0,
      "pick_cover_prob": null,
      "pick_ev_per_1": null,
      "pick_fair_odds": null,
      "pick_prob_edge": null,
      "pick_side": "AWAY",
      "pick_spread_odds": null,
      "pred_home_win_prob": 0.3675765009834918,
      "pred_sigma": 10.369279
    },
    {
      "away_team": "St. Bonaventure",
      "edge_home_points": null,
      "game_id": "2025_11_30_st_bonaventure_florida_atlantic",
      "home_team": "Florida Atlantic",
      "market_spread_home": null,
      "model_mu_home": -2.1844492,
      "neutral_site": 0,
      "pick_cover_prob": null,
      "pick_ev_per_1": null,
      "pick_fair_odds": null,
      "pick_prob_edge": null,
      "pick_side": "AWAY",
      "pick_spread_odds": null,
      "pred_home_win_prob": 0.59883685923559,
      "pred_sigma": 8.726013
    },
    {
      "away_team": "Prairie View A&M",
      "edge_home_points": null,
      "game_id": "2025_11_30_prairie_view_a_m_north_texas",
      "home_team": "North Texas",
      "market_spread_home": null,
      "model_mu_home": -18.500784,
      "neutral_site": 0,
      "pick_cover_prob": null,
      "pick_ev_per_1": null,
      "pick_fair_odds": null,
      "pick_prob_edge": null,
      "pick_side": "AWAY",
      "pick_spread_odds": null,
      "pred_home_win_prob": 0.958972877425288,
      "pred_sigma": 10.639426
    },
    {
      "away_team": "UC Irvine",
      "edge_home_points": null,
      "game_id": "2025_11_30_uc_irvine_san_jose_st",
      "home_team": "San Jose St.",
      "market_spread_home": null,
      "model_mu_home": 4.569718,
      "neutral_site": 0,
      "pick_cover_prob": null,
      "pick_ev_per_1": null,
      "pick_fair_odds": null,
      "pick_prob_edge": null,
      "pick_side": "AWAY",
      "pick_spread_odds": null,
      "pred_home_win_prob": 0.3085978611928457,
      "pred_sigma": 9.142569
    },
    {
      "away_team": "Colgate",
      "edge_home_points": null,
      "game_id": "2025_11_30_colgate_fordham",
      "home_team": "Fordham",
      "market_spread_home": null,
      "model_mu_home": -1.6054518,
      "neutral_site": 1,
      "pick_cover_prob": null,
      "pick_ev_per_1": null,
      "pick_fair_odds": null,
      "pick_prob_edge": null,
      "pick_side": "AWAY",
      "pick_spread_odds": null,
      "pred_home_win_prob": 0.5638568455223347,
      "pred_sigma": 9.986943
    },
    {
      "away_team": "Old Dominion",
      "edge_home_points": null,
      "game_id": "2025_11_30_old_dominion_william_mary",
      "home_team": "William & Mary",
      "market_spread_home": null,
      "model_mu_home": -7.9757195,
      "neutral_site": 0,
      "pick_cover_prob": null,
      "pick_ev_per_1": null,
      "pick_fair_odds": null,
      "pick_prob_edge": null,
      "pick_side": "AWAY",
      "pick_spread_odds": null,
      "pred_home_win_prob": 0.8094370923045852,
      "pred_sigma": 9.106534
    },
    {
      "away_team": "Cornell",
      "edge_home_points": null,
      "game_id": "2025_11_30_cornell_bucknell",
      "home_team": "Bucknell",
      "market_spread_home": null,
      "model_mu_home": 4.038759,
      "neutral_site": 0,
      "pick_cover_prob": null,
      "pick_ev_per_1": null,
      "pick_fair_odds": null,
      "pick_prob_edge": null,
      "pick_side": "AWAY",
      "pick_spread_odds": null,
      "pred_home_win_prob": 0.363637721849737,
      "pred_sigma": 11.580603
    },
    {
      "away_team": "Wyoming",
      "edge_home_points": null,
      "game_id": "2025_11_30_wyoming_texas_tech",
      "home_team": "Texas Tech",
      "market_spread_home": null,
      "model_mu_home": -15.794311,
      "neutral_site": 0,
      "pick_cover_prob": null,
      "pick_ev_per_1": null,
      "pick_fair_odds": null,
      "pick_prob_edge": null,
      "pick_side": "AWAY",
      "pick_spread_odds": null,
      "pred_home_win_prob": 0.939489356801704,
      "pred_sigma": 10.186584
    },
    {
      "away_team": "New Hampshire",
      "edge_home_points": null,
      "game_id": "2025_11_30_new_hampshire_fairfield",
      "home_team": "Fairfield",
      "market_spread_home": null,
      "model_mu_home": -6.437073,
      "neutral_site": 0,
      "pick_cover_prob": null,
      "pick_ev_per_1": null,
      "pick_fair_odds": null,
      "pick_prob_edge": null,
      "pick_side": "AWAY",
      "pick_spread_odds": null,
      "pred_home_win_prob": 0.7499998905887398,
      "pred_sigma": 9.543624
    }
  ],
  "generated_at": "2026-01-22T18:39:32.839947Z"
}
